gdrive_connector.py
google_drive_connector_danish-1.0.1.dist-info/METADATA
google_drive_connector_danish-1.0.1.dist-info/WHEEL
google_drive_connector_danish-1.0.1.dist-info/top_level.txt
google_drive_connector_danish-1.0.1.dist-info/RECORD
