Metadata-Version: 2.4
Name: google_drive_connector_danish
Version: 1.0.1
Summary: A utility class to interact with Google Drive using OAuth 2.0 credentials.
Author: Danish
Author-email: tabnoone@gmail.com
Requires-Python: >=3.8
Requires-Dist: google-api-python-client==2.179.0
Requires-Dist: google-auth==2.40.3
Requires-Dist: python-dotenv==1.1.1
Dynamic: author
Dynamic: author-email
Dynamic: description
Dynamic: description-content-type
Dynamic: requires-dist
Dynamic: requires-python
Dynamic: summary
